{
    "version": "0.7.82",
    "description": "Autorizovana konverze dokumentu (I.CA / PostSignum, Czech POINT)",
    "homepage": "https://konverze.pravnikovo.info",
    "license": "Proprietary",
    "architecture": {
        "64bit": {
            "url": "https://konverze.pravnikovo.info/konverze-v0.7.82-portable-win64.zip",
            "hash": "de06b6b59f0b80be13114bb9f8180049aced955ee2673f052b496127dc64e019",
            "extract_dir": "konverze"
        }
    },
    "bin": "konverze.exe",
    "shortcuts": [
        [
            "konverze.exe",
            "Konverze"
        ]
    ],
    "checkver": {
        "url": "https://konverze.pravnikovo.info/api/license.php?action=status",
        "jsonpath": "$.latest_version"
    },
    "autoupdate": {
        "architecture": {
            "64bit": {
                "url": "https://konverze.pravnikovo.info/konverze-v$version-portable-win64.zip"
            }
        }
    }
}
